Verilog/dff/dff.v
module dff(
    input d_in,
    input clk,
    input rst,
    output reg q_out);
    always @(posedge clk or posedge rst) begin
        if (rst)
            q_out <= 1'b0;
        else
            q_out <= d_in;
    end
endmodule

Verilog/dff/dff_tb.v
`timescale 1ns/1ps

module dff_tb;
    reg d_in, clk, rst;
    wire q_out;

    dff u1 (d_in, clk, rst, q_out);

    initial begin
        clk = 0;
        forever #5 clk = ~clk;
    end

    initial begin
        $dumpfile("dff_async_tb.vcd");
        $dumpvars(0, dff_tb);

        rst = 1; #10;
        rst = 0; #10;
        d_in = 1; #10;
        d_in = 0; #10;
        d_in = 1; #10;
        d_in = 0; #10;
        d_in = 1; #10;
        d_in = 0; #10;

        $finish;
    end
endmodule

Verilog/dff/dff_async_tb.vcd
$date
	Wed Dec  3 06:35:25 2025
$end
$version
	Icarus Verilog
$end
$timescale
	1ps
$end
$scope module dff_tb $end
$var wire 1 ! q_out $end
$var reg 1 " clk $end
$var reg 1 # d_in $end
$var reg 1 $ rst $end
$scope module u1 $end
$var wire 1 " clk $end
$var wire 1 # d_in $end
$var wire 1 $ rst $end
$var reg 1 ! q_out $end
$upscope $end
$upscope $end
$enddefinitions $end
$comment Show the parameter values. $end
$dumpall
$end
#0
$dumpvars
1$
x#
0"
0!
$end
#5000
1"
#10000
0"
0$
#15000
x!
1"
#20000
0"
1#
#25000
1!
1"
#30000
0"
0#
#35000
0!
1"
#40000
0"
1#
#45000
1!
1"
#50000
0"
0#
#55000
0!
1"
#60000
0"
1#
#65000
1!
1"
#70000
0"
0#
#75000
0!
1"
