Verilog/sumblock/sum_block.v
module sum_block(A, B, C, P_inv, G_inv, S);
    input A, B, C;
    output P_inv, G_inv, S;
    wire midsum;   
    nor n1(P_inv, A, B);
    nand n2(G_inv, A, B);
    xor x1(midsum, A, B);
    xor x2(S, midsum, C);
endmodule

Verilog/sumblock/sb_tb.v
`timescale 1ns/1ps

module tb_sum_block;
    reg A, B, C;
    wire P_inv, G_inv, S;
    
    sum_block dut(
        .A(A),
        .B(B),
        .C(C),
        .P_inv(P_inv),
        .G_inv(G_inv),
        .S(S)
    );
    
    initial begin
        $dumpfile("sum_block.vcd");
        $dumpvars(0, tb_sum_block);
        
        A = 0; B = 0; C = 0;
        #10;
        $display("A=%b, B=%b, C=%b | P_inv=%b, G_inv=%b, S=%b", A, B, C, P_inv, G_inv,S);
        
        A = 0; B = 0; C = 1;
        #10;
        $display("A=%b, B=%b, C=%b | P_inv=%b, G_inv=%b, S=%b", A, B, C, P_inv, G_inv,S);
        
        A = 0; B = 1; C = 0;
        #10;
        $display("A=%b, B=%b, C=%b | P_inv=%b, G_inv=%b, S=%b", A, B, C, P_inv, G_inv,S);
        
        A = 0; B = 1; C = 1;
        #10;
        $display("A=%b, B=%b, C=%b | P_inv=%b, G_inv=%b, S=%b", A, B, C, P_inv, G_inv,S);
        
        A = 1; B = 0; C = 0;
        #10;
        $display("A=%b, B=%b, C=%b | P_inv=%b, G_inv=%b, S=%b", A, B, C, P_inv, G_inv,S);
        
        A = 1; B = 0; C = 1;
        #10;
        $display("A=%b, B=%b, C=%b | P_inv=%b, G_inv=%b, S=%b", A, B, C, P_inv, G_inv,S);
        
        A = 1; B = 1; C = 0;
        #10;
        $display("A=%b, B=%b, C=%b | P_inv=%b, G_inv=%b, S=%b", A, B, C, P_inv, G_inv,S);
        
        A = 1; B = 1; C = 1;
        #10;
        $display("A=%b, B=%b, C=%b | P_inv=%b, G_inv=%b, S=%b", A, B, C, P_inv, G_inv,S);
        
        #10;
        $finish;
    end
    
endmodule

Verilog/sumblock/sum_block.vcd
$date
	Wed Dec  3 06:30:06 2025
$end
$version
	Icarus Verilog
$end
$timescale
	1ps
$end
$scope module tb_sum_block $end
$var wire 1 ! S $end
$var wire 1 " P_inv $end
$var wire 1 # G_inv $end
$var reg 1 $ A $end
$var reg 1 % B $end
$var reg 1 & C $end
$scope module dut $end
$var wire 1 $ A $end
$var wire 1 % B $end
$var wire 1 & C $end
$var wire 1 # G_inv $end
$var wire 1 " P_inv $end
$var wire 1 ! S $end
$var wire 1 ' midsum $end
$upscope $end
$upscope $end
$enddefinitions $end
$comment Show the parameter values. $end
$dumpall
$end
#0
$dumpvars
0'
0&
0%
0$
1#
1"
0!
$end
#10000
1!
1&
#20000
0"
1'
0&
1%
#30000
0!
1&
#40000
1!
0&
0%
1$
#50000
0!
1&
#60000
0#
0'
0&
1%
#70000
1!
1&
