Verilog/fullckt/circuit.v
module sum_block(A, B, C, P_inv, G_inv, S);
    input A, B, C;
    output P_inv, G_inv, S;
    wire midsum;   
    nor n1(P_inv, A, B);
    nand n2(G_inv, A, B);
    xor x1(midsum, A, B);
    xor x2(S, midsum, C);
endmodule

module d_ff (D, CLK, RST, Q);
  input D, CLK, RST;
  output reg Q;
  always @(posedge CLK or posedge RST) begin
    if (RST)
      Q = 1'b0;
    else
      Q = D;
  end
endmodule

module CLA(
    input a0, b0, a1, b1, a2, b2, a3, b3, a4, b4,
    input c0,      
    output s0, s1, s2, s3, s4,
    output c5     
);
    wire g0_inv, g1_inv, g2_inv, g3_inv, gen4_inv;
    wire p0_inv, p1_inv, p2_inv, p3_inv, prop4_inv;
    wire c1, c2, c3, c4, c4_inv;
    wire c0_inv;
    wire p1, p2, p3, p4, p5, p6, p7, p8;
    wire g1, g2, g3, g4, g5, g6, g7;
    wire p9, p10;
    wire midsum4;
    
    sum_block sb0(.A(a0), .B(b0), .C(c0), .P_inv(p0_inv), .G_inv(g0_inv), .S(s0));
    
    assign c0_inv = ~c0;
    assign p1 = p0_inv | c0_inv;
    assign c1 = ~(p1 & g0_inv);
    
    sum_block sb1(.A(a1), .B(b1), .C(c1), .P_inv(p1_inv), .G_inv(g1_inv), .S(s1));
    
    assign p2 = ~(p1_inv | p0_inv);
    assign g1 = p2 & c0;
    assign p3 = g0_inv | p1_inv;
    assign g2 = ~(p3 & g1_inv);
    assign c2 = g2 | g1;
    
    sum_block sb2(.A(a2), .B(b2), .C(c2), .P_inv(p2_inv), .G_inv(g2_inv), .S(s2));
    
    assign p4 = ~(p1_inv | p2_inv);
    assign g3 = p4 & c1;
    assign p5 = g1_inv | p2_inv;
    assign g4 = ~(p5 & g2_inv);
    assign c3 = g4 | g3;
    
    sum_block sb3(.A(a3), .B(b3), .C(c3), .P_inv(p3_inv), .G_inv(g3_inv), .S(s3));
    
    assign p6 = ~(p3_inv | p2_inv);
    assign p7 = p6 & p2;
    assign p8 = g2 & p6;
    assign g5 = g2_inv | p3_inv;
    assign g6 = ~(g5 & g3_inv);
    assign g7 = ~(g6 | p8);
    assign p9 = ~(p7 & c0);
    assign c4 = ~(p9 & g7);
    
    assign gen4_inv = ~(a4 & b4);
    assign prop4_inv = ~(a4 | b4);
    assign midsum4 = a4 ^ b4;
    assign s4 = midsum4 ^ c4;
    assign c4_inv = ~c4;
    assign p10 = prop4_inv | c4_inv;
    assign c5 = ~(p10 & gen4_inv);
    
endmodule

module cla5bit(
    input a0, b0, a1, b1, a2, b2, a3, b3, a4, b4,
    input c0,
    input clk,
    output s0, s1, s2, s3, s4,
    output c5
);
    wire a0_reg, b0_reg, a1_reg, b1_reg;
    wire a2_reg, b2_reg, a3_reg, b3_reg;
    wire a4_reg, b4_reg;
    wire c0_reg;
    wire s0_cla, s1_cla, s2_cla, s3_cla, s4_cla;
    wire c5_cla;
    
    d_ff ff_a0(.D(a0), .CLK(clk), .RST(1'b0), .Q(a0_reg));
    d_ff ff_b0(.D(b0), .CLK(clk), .RST(1'b0), .Q(b0_reg));
    d_ff ff_a1(.D(a1), .CLK(clk), .RST(1'b0), .Q(a1_reg));
    d_ff ff_b1(.D(b1), .CLK(clk), .RST(1'b0), .Q(b1_reg));
    d_ff ff_a2(.D(a2), .CLK(clk), .RST(1'b0), .Q(a2_reg));
    d_ff ff_b2(.D(b2), .CLK(clk), .RST(1'b0), .Q(b2_reg));
    d_ff ff_a3(.D(a3), .CLK(clk), .RST(1'b0), .Q(a3_reg));
    d_ff ff_b3(.D(b3), .CLK(clk), .RST(1'b0), .Q(b3_reg));
    d_ff ff_a4(.D(a4), .CLK(clk), .RST(1'b0), .Q(a4_reg));
    d_ff ff_b4(.D(b4), .CLK(clk), .RST(1'b0), .Q(b4_reg));
    d_ff ff_c0(.D(c0), .CLK(clk), .RST(1'b0), .Q(c0_reg));
    
    CLA cla_inst(
        .a0(a0_reg), .b0(b0_reg),
        .a1(a1_reg), .b1(b1_reg),
        .a2(a2_reg), .b2(b2_reg),
        .a3(a3_reg), .b3(b3_reg),
        .a4(a4_reg), .b4(b4_reg),
        .c0(c0_reg),
        .s0(s0_cla), .s1(s1_cla),
        .s2(s2_cla), .s3(s3_cla),
        .s4(s4_cla),
        .c5(c5_cla)
    );
    
    d_ff ff_s0(.D(s0_cla), .CLK(clk), .RST(1'b0), .Q(s0));
    d_ff ff_s1(.D(s1_cla), .CLK(clk), .RST(1'b0), .Q(s1));
    d_ff ff_s2(.D(s2_cla), .CLK(clk), .RST(1'b0), .Q(s2));
    d_ff ff_s3(.D(s3_cla), .CLK(clk), .RST(1'b0), .Q(s3));
    d_ff ff_s4(.D(s4_cla), .CLK(clk), .RST(1'b0), .Q(s4));
    d_ff ff_c5(.D(c5_cla), .CLK(clk), .RST(1'b0), .Q(c5));
    
endmodule

Verilog/fullckt/circuit_tb.v
`timescale 1ns/1ps

module cla5bit_tb;
    reg a0, b0, a1, b1, a2, b2, a3, b3, a4, b4;
    reg c0;
    reg clk;
    wire s0, s1, s2, s3, s4;
    wire c5;
    
    reg [4:0] A, B;
    wire [4:0] sum_out;
    
    assign sum_out = {s4, s3, s2, s1, s0};
    
    cla5bit dut(
        .a0(a0), .b0(b0), .a1(a1), .b1(b1),
        .a2(a2), .b2(b2), .a3(a3), .b3(b3),
        .a4(a4), .b4(b4),
        .c0(c0),
        .clk(clk),
        .s0(s0), .s1(s1), .s2(s2), .s3(s3), .s4(s4),
        .c5(c5)
    );
    
    initial begin
        clk = 0;
        forever #5 clk = ~clk;
    end
    
    initial begin
        $dumpfile("cla_5bit.vcd");
        $dumpvars(0, cla5bit_tb);        
        #10;
        
        A = 5'd15; B = 5'd10; c0 = 1'b0;
        {a4, a3, a2, a1, a0} = A;
        {b4, b3, b2, b1, b0} = B;
        @(posedge clk);
        #1;
        @(posedge clk);
        #2;
        $display("A=%d, B=%d, Cin=%d | Sum=%d, Cout=%d", A, B, c0, sum_out, c5);
        
        A = 5'd31; B = 5'd15; c0 = 1'b1;
        {a4, a3, a2, a1, a0} = A;
        {b4, b3, b2, b1, b0} = B;
        @(posedge clk);
        #1;
        @(posedge clk);
        #2;
        $display("A=%d, B=%d, Cin=%d | Sum=%d, Cout=%d", A, B, c0, sum_out, c5);
        
        A = 5'd7; B = 5'd8; c0 = 1'b1;
        {a4, a3, a2, a1, a0} = A;
        {b4, b3, b2, b1, b0} = B;
        @(posedge clk);
        #1;
        @(posedge clk);
        #2;
        $display("A=%d, B=%d, Cin=%d | Sum=%d, Cout=%d", A, B, c0, sum_out, c5);
        
        A = 5'd20; B = 5'd11; c0 = 1'b0;
        {a4, a3, a2, a1, a0} = A;
        {b4, b3, b2, b1, b0} = B;
        @(posedge clk);
        #1;
        @(posedge clk);
        #2;
        $display("A=%d, B=%d, Cin=%d | Sum=%d, Cout=%d", A, B, c0, sum_out, c5);
        
        A = 5'd0; B = 5'd0; c0 = 1'b1;
        {a4, a3, a2, a1, a0} = A;
        {b4, b3, b2, b1, b0} = B;
        @(posedge clk);
        #1;
        @(posedge clk);
        #2;
        $display("A=%d, B=%d, Cin=%d | Sum=%d, Cout=%d", A, B, c0, sum_out, c5);
        
        A = 5'd31; B = 5'd31; c0 = 1'b1;
        {a4, a3, a2, a1, a0} = A;
        {b4, b3, b2, b1, b0} = B;
        @(posedge clk);
        #1;
        @(posedge clk);
        #2;
        $display("A=%d, B=%d, Cin=%d | Sum=%d, Cout=%d", A, B, c0, sum_out, c5);
        
        #50;
        $finish;
    end
    
endmodule

Verilog/fullckt/cla_5bit.vcd
$date
	Wed Dec  3 05:54:34 2025
$end
$version
	Icarus Verilog
$end
$timescale
	1ps
$end
$scope module cla5bit_tb $end
$var wire 5 ! sum_out [4:0] $end
$var wire 1 " s4 $end
$var wire 1 # s3 $end
$var wire 1 $ s2 $end
$var wire 1 % s1 $end
$var wire 1 & s0 $end
$var wire 1 ' c5 $end
$var reg 5 ( A [4:0] $end
$var reg 5 ) B [4:0] $end
$var reg 1 * a0 $end
$var reg 1 + a1 $end
$var reg 1 , a2 $end
$var reg 1 - a3 $end
$var reg 1 . a4 $end
$var reg 1 / b0 $end
$var reg 1 0 b1 $end
$var reg 1 1 b2 $end
$var reg 1 2 b3 $end
$var reg 1 3 b4 $end
$var reg 1 4 c0 $end
$var reg 1 5 clk $end
$scope module dut $end
$var wire 1 * a0 $end
$var wire 1 + a1 $end
$var wire 1 , a2 $end
$var wire 1 - a3 $end
$var wire 1 . a4 $end
$var wire 1 / b0 $end
$var wire 1 0 b1 $end
$var wire 1 1 b2 $end
$var wire 1 2 b3 $end
$var wire 1 3 b4 $end
$var wire 1 4 c0 $end
$var wire 1 5 clk $end
$var wire 1 6 s4_cla $end
$var wire 1 " s4 $end
$var wire 1 7 s3_cla $end
$var wire 1 # s3 $end
$var wire 1 8 s2_cla $end
$var wire 1 $ s2 $end
$var wire 1 9 s1_cla $end
$var wire 1 % s1 $end
$var wire 1 : s0_cla $end
$var wire 1 & s0 $end
$var wire 1 ; c5_cla $end
$var wire 1 ' c5 $end
$var wire 1 < c0_reg $end
$var wire 1 = b4_reg $end
$var wire 1 > b3_reg $end
$var wire 1 ? b2_reg $end
$var wire 1 @ b1_reg $end
$var wire 1 A b0_reg $end
$var wire 1 B a4_reg $end
$var wire 1 C a3_reg $end
$var wire 1 D a2_reg $end
$var wire 1 E a1_reg $end
$var wire 1 F a0_reg $end
$scope module cla_inst $end
$var wire 1 G c0_inv $end
$var wire 1 H c1 $end
$var wire 1 I c2 $end
$var wire 1 J c3 $end
$var wire 1 K c4 $end
$var wire 1 L c4_inv $end
$var wire 1 ; c5 $end
$var wire 1 M g1 $end
$var wire 1 N g2 $end
$var wire 1 O g3 $end
$var wire 1 P g4 $end
$var wire 1 Q g5 $end
$var wire 1 R g6 $end
$var wire 1 S g7 $end
$var wire 1 T gen4_inv $end
$var wire 1 U midsum4 $end
$var wire 1 V p1 $end
$var wire 1 W p10 $end
$var wire 1 X p2 $end
$var wire 1 Y p3 $end
$var wire 1 Z p4 $end
$var wire 1 [ p5 $end
$var wire 1 \ p6 $end
$var wire 1 ] p7 $end
$var wire 1 ^ p8 $end
$var wire 1 _ p9 $end
$var wire 1 ` prop4_inv $end
$var wire 1 6 s4 $end
$var wire 1 7 s3 $end
$var wire 1 8 s2 $end
$var wire 1 9 s1 $end
$var wire 1 : s0 $end
$var wire 1 a p3_inv $end
$var wire 1 b p2_inv $end
$var wire 1 c p1_inv $end
$var wire 1 d p0_inv $end
$var wire 1 e g3_inv $end
$var wire 1 f g2_inv $end
$var wire 1 g g1_inv $end
$var wire 1 h g0_inv $end
$var wire 1 < c0 $end
$var wire 1 = b4 $end
$var wire 1 > b3 $end
$var wire 1 ? b2 $end
$var wire 1 @ b1 $end
$var wire 1 A b0 $end
$var wire 1 B a4 $end
$var wire 1 C a3 $end
$var wire 1 D a2 $end
$var wire 1 E a1 $end
$var wire 1 F a0 $end
$scope module sb0 $end
$var wire 1 h G_inv $end
$var wire 1 d P_inv $end
$var wire 1 : S $end
$var wire 1 i midsum $end
$var wire 1 < C $end
$var wire 1 A B $end
$var wire 1 F A $end
$upscope $end
$scope module sb1 $end
$var wire 1 H C $end
$var wire 1 g G_inv $end
$var wire 1 c P_inv $end
$var wire 1 9 S $end
$var wire 1 j midsum $end
$var wire 1 @ B $end
$var wire 1 E A $end
$upscope $end
$scope module sb2 $end
$var wire 1 I C $end
$var wire 1 f G_inv $end
$var wire 1 b P_inv $end
$var wire 1 8 S $end
$var wire 1 k midsum $end
$var wire 1 ? B $end
$var wire 1 D A $end
$upscope $end
$scope module sb3 $end
$var wire 1 J C $end
$var wire 1 e G_inv $end
$var wire 1 a P_inv $end
$var wire 1 7 S $end
$var wire 1 l midsum $end
$var wire 1 > B $end
$var wire 1 C A $end
$upscope $end
$upscope $end
$scope module ff_a0 $end
$var wire 1 5 CLK $end
$var wire 1 * D $end
$var wire 1 m RST $end
$var reg 1 F Q $end
$upscope $end
$scope module ff_a1 $end
$var wire 1 5 CLK $end
$var wire 1 + D $end
$var wire 1 n RST $end
$var reg 1 E Q $end
$upscope $end
$scope module ff_a2 $end
$var wire 1 5 CLK $end
$var wire 1 , D $end
$var wire 1 o RST $end
$var reg 1 D Q $end
$upscope $end
$scope module ff_a3 $end
$var wire 1 5 CLK $end
$var wire 1 - D $end
$var wire 1 p RST $end
$var reg 1 C Q $end
$upscope $end
$scope module ff_a4 $end
$var wire 1 5 CLK $end
$var wire 1 . D $end
$var wire 1 q RST $end
$var reg 1 B Q $end
$upscope $end
$scope module ff_b0 $end
$var wire 1 5 CLK $end
$var wire 1 / D $end
$var wire 1 r RST $end
$var reg 1 A Q $end
$upscope $end
$scope module ff_b1 $end
$var wire 1 5 CLK $end
$var wire 1 0 D $end
$var wire 1 s RST $end
$var reg 1 @ Q $end
$upscope $end
$scope module ff_b2 $end
$var wire 1 5 CLK $end
$var wire 1 1 D $end
$var wire 1 t RST $end
$var reg 1 ? Q $end
$upscope $end
$scope module ff_b3 $end
$var wire 1 5 CLK $end
$var wire 1 2 D $end
$var wire 1 u RST $end
$var reg 1 > Q $end
$upscope $end
$scope module ff_b4 $end
$var wire 1 5 CLK $end
$var wire 1 3 D $end
$var wire 1 v RST $end
$var reg 1 = Q $end
$upscope $end
$scope module ff_c0 $end
$var wire 1 5 CLK $end
$var wire 1 4 D $end
$var wire 1 w RST $end
$var reg 1 < Q $end
$upscope $end
$scope module ff_c5 $end
$var wire 1 5 CLK $end
$var wire 1 ; D $end
$var wire 1 x RST $end
$var reg 1 ' Q $end
$upscope $end
$scope module ff_s0 $end
$var wire 1 5 CLK $end
$var wire 1 : D $end
$var wire 1 y RST $end
$var reg 1 & Q $end
$upscope $end
$scope module ff_s1 $end
$var wire 1 5 CLK $end
$var wire 1 9 D $end
$var wire 1 z RST $end
$var reg 1 % Q $end
$upscope $end
$scope module ff_s2 $end
$var wire 1 5 CLK $end
$var wire 1 8 D $end
$var wire 1 { RST $end
$var reg 1 $ Q $end
$upscope $end
$scope module ff_s3 $end
$var wire 1 5 CLK $end
$var wire 1 7 D $end
$var wire 1 | RST $end
$var reg 1 # Q $end
$upscope $end
$scope module ff_s4 $end
$var wire 1 5 CLK $end
$var wire 1 6 D $end
$var wire 1 } RST $end
$var reg 1 " Q $end
$upscope $end
$upscope $end
$upscope $end
$enddefinitions $end
$comment Show the parameter values. $end
$dumpall
$end
#0
$dumpvars
0}
0|
0{
0z
0y
0x
0w
0v
0u
0t
0s
0r
0q
0p
0o
0n
0m
xl
xk
xj
xi
xh
xg
xf
xe
xd
xc
xb
xa
x`
x_
x^
x]
x\
x[
xZ
xY
xX
xW
xV
xU
xT
xS
xR
xQ
xP
xO
xN
xM
xL
xK
xJ
xI
xH
xG
xF
xE
xD
xC
xB
xA
x@
x?
x>
x=
x<
x;
x:
x9
x8
x7
x6
05
x4
x3
x2
x1
x0
x/
x.
x-
x,
x+
x*
bx )
bx (
x'
x&
x%
x$
x#
x"
bx !
$end
#5000
15
#10000
05
03
12
01
10
0/
0.
1-
1,
1+
1*
04
b1010 )
b1111 (
#15000
16
0L
1K
08
17
0S
0;
09
1I
1J
0O
1]
1^
0H
1N
1X
1P
1Z
1R
1\
1W
1:
1Y
0[
1Q
1`
1T
1_
1V
1i
1h
0d
0j
0g
0c
1k
1f
0b
0l
0e
0a
0U
0M
1G
1F
1E
1D
1C
0B
0A
1@
0?
1>
0=
0<
15
#20000
05
#25000
0'
1&
0%
0$
1#
b11001 !
1"
15
#27000
11
1/
1.
14
b1111 )
b11111 (
#30000
05
#35000
1;
1O
19
0W
1H
06
0`
0Y
18
0Q
0_
0V
1U
0i
0h
0k
0f
1:
1M
0G
1B
1A
1?
1<
15
#40000
05
#45000
1'
1%
1$
b1111 !
0"
15
#47000
01
00
0/
0.
0-
b1000 )
b111 (
#50000
05
#55000
1S
0;
0^
0N
0P
0R
1W
07
16
1`
0:
1Y
09
1[
08
1Q
1l
1e
0U
1i
1h
1j
1g
1k
1f
0C
0B
0A
0@
0?
15
#60000
05
#65000
0'
0&
0%
0$
0#
b10000 !
1"
15
#67000
10
1/
1.
0+
0*
04
b1011 )
b10100 (
#70000
05
#75000
17
0J
0;
1L
0O
19
0K
0H
1W
18
16
0`
1_
0I
1V
1U
1:
0M
1G
0F
0E
1B
1A
1@
0<
15
#80000
05
#85000
1&
1%
1$
b11111 !
1#
15
#87000
02
00
0/
0.
0,
14
b0 )
b0 (
#90000
05
#95000
08
1L
0]
0K
0Z
0X
0\
06
1`
09
07
1_
0I
0k
1b
0U
0i
1d
0j
1c
0l
1a
1:
0M
0G
0D
0B
0A
0@
0>
1<
15
#100000
05
#105000
0%
0$
0#
b1 !
0"
15
#107000
13
12
11
10
1/
1.
1-
1,
1+
1*
b11111 )
b11111 (
#110000
05
#115000
0W
16
0L
1K
0_
18
17
0S
19
1I
1M
1J
1O
1]
1^
1;
1H
1N
1X
1P
1Z
1R
1\
0V
0Y
0[
0Q
0`
0T
0h
0d
0g
0c
0f
0b
0e
0a
1F
1E
1D
1C
1B
1A
1@
1?
1>
1=
15
#120000
05
#125000
1'
1%
1$
1#
b11111 !
1"
15
